<?xml version="1.0" encoding="Windows-1252"?>
<BalanceSheets xmlns:xsi="http://www.w3.org/2001/XMLSchema-instance" xmlns:xsd="http://www.w3.org/2001/XMLSchema">
  <BalanceSheetArray>
    <BalanceSheetObject>
      <dayOfTheMonth>29</dayOfTheMonth>
      <month>January</month>
      <year>2017</year>
      <day>Sunday</day>
      <numberOfWeeks>4</numberOfWeeks>
      <cashAtBank>222041.859</cashAtBank>
      <accountsReceivable>27139.86</accountsReceivable>
      <inventories>13757</inventories>
      <totalCurrentAssets>240896.859</totalCurrentAssets>
      <propretyAndEquipment>5200641</propretyAndEquipment>
      <totalAssets>5441538</totalAssets>
      <accountsPayable>16128</accountsPayable>
      <carbonOffsetReceipts>0</carbonOffsetReceipts>
      <incomeTaxPayable>0</incomeTaxPayable>
      <dividendOwed>0</dividendOwed>
      <currentMaturityofLongtermDebt>0</currentMaturityofLongtermDebt>
      <totalCurrentLiabilities>16128</totalCurrentLiabilities>
      <longTermDebt>0</longTermDebt>
      <shareCapital>4750000</shareCapital>
      <retainedEarnings>136295</retainedEarnings>
      <ownersEquity>4886295</ownersEquity>
      <totalLiabilitiesAndOwnersEquity>5487819</totalLiabilitiesAndOwnersEquity>
    </BalanceSheetObject>
    <BalanceSheetObject>
      <dayOfTheMonth>26</dayOfTheMonth>
      <month>February</month>
      <year>2017</year>
      <day>Sunday</day>
      <numberOfWeeks>4</numberOfWeeks>
      <cashAtBank>242174.188</cashAtBank>
      <accountsReceivable>25715.334</accountsReceivable>
      <inventories>13757</inventories>
      <totalCurrentAssets>261514.188</totalCurrentAssets>
      <propretyAndEquipment>5200641</propretyAndEquipment>
      <totalAssets>5462155</totalAssets>
      <accountsPayable>16128</accountsPayable>
      <carbonOffsetReceipts>0</carbonOffsetReceipts>
      <incomeTaxPayable>0</incomeTaxPayable>
      <dividendOwed>0</dividendOwed>
      <currentMaturityofLongtermDebt>0</currentMaturityofLongtermDebt>
      <totalCurrentLiabilities>16128</totalCurrentLiabilities>
      <longTermDebt>0</longTermDebt>
      <shareCapital>4750000</shareCapital>
      <retainedEarnings>136295</retainedEarnings>
      <ownersEquity>4886295</ownersEquity>
      <totalLiabilitiesAndOwnersEquity>5487819</totalLiabilitiesAndOwnersEquity>
    </BalanceSheetObject>
    <BalanceSheetObject>
      <dayOfTheMonth>2</dayOfTheMonth>
      <month>April</month>
      <year>2017</year>
      <day>Sunday</day>
      <numberOfWeeks>4</numberOfWeeks>
      <cashAtBank>267787.063</cashAtBank>
      <accountsReceivable>32442.8652</accountsReceivable>
      <inventories>13757</inventories>
      <totalCurrentAssets>288374.063</totalCurrentAssets>
      <propretyAndEquipment>5200641</propretyAndEquipment>
      <totalAssets>5489015</totalAssets>
      <accountsPayable>20160</accountsPayable>
      <carbonOffsetReceipts>0</carbonOffsetReceipts>
      <incomeTaxPayable>0</incomeTaxPayable>
      <dividendOwed>0</dividendOwed>
      <currentMaturityofLongtermDebt>0</currentMaturityofLongtermDebt>
      <totalCurrentLiabilities>20160</totalCurrentLiabilities>
      <longTermDebt>0</longTermDebt>
      <shareCapital>4750000</shareCapital>
      <retainedEarnings>136295</retainedEarnings>
      <ownersEquity>4886295</ownersEquity>
      <totalLiabilitiesAndOwnersEquity>5487819</totalLiabilitiesAndOwnersEquity>
    </BalanceSheetObject>
    <BalanceSheetObject>
      <dayOfTheMonth>30</dayOfTheMonth>
      <month>April</month>
      <year>2017</year>
      <day>Sunday</day>
      <numberOfWeeks>4</numberOfWeeks>
      <cashAtBank>287919.5</cashAtBank>
      <accountsReceivable>25650.4336</accountsReceivable>
      <inventories>13757</inventories>
      <totalCurrentAssets>307194.5</totalCurrentAssets>
      <propretyAndEquipment>5200641</propretyAndEquipment>
      <totalAssets>5507835.5</totalAssets>
      <accountsPayable>16128</accountsPayable>
      <carbonOffsetReceipts>0</carbonOffsetReceipts>
      <incomeTaxPayable>0</incomeTaxPayable>
      <dividendOwed>0</dividendOwed>
      <currentMaturityofLongtermDebt>0</currentMaturityofLongtermDebt>
      <totalCurrentLiabilities>16128</totalCurrentLiabilities>
      <longTermDebt>0</longTermDebt>
      <shareCapital>4750000</shareCapital>
      <retainedEarnings>136295</retainedEarnings>
      <ownersEquity>4886295</ownersEquity>
      <totalLiabilitiesAndOwnersEquity>5487819</totalLiabilitiesAndOwnersEquity>
    </BalanceSheetObject>
    <BalanceSheetObject>
      <dayOfTheMonth>4</dayOfTheMonth>
      <month>June</month>
      <year>2017</year>
      <day>Sunday</day>
      <numberOfWeeks>4</numberOfWeeks>
      <cashAtBank>313407.5</cashAtBank>
      <accountsReceivable>32323.0156</accountsReceivable>
      <inventories>13757</inventories>
      <totalCurrentAssets>333999.5</totalCurrentAssets>
      <propretyAndEquipment>5200641</propretyAndEquipment>
      <totalAssets>5534640.5</totalAssets>
      <accountsPayable>20160</accountsPayable>
      <carbonOffsetReceipts>0</carbonOffsetReceipts>
      <incomeTaxPayable>0</incomeTaxPayable>
      <dividendOwed>0</dividendOwed>
      <currentMaturityofLongtermDebt>0</currentMaturityofLongtermDebt>
      <totalCurrentLiabilities>20160</totalCurrentLiabilities>
      <longTermDebt>0</longTermDebt>
      <shareCapital>4750000</shareCapital>
      <retainedEarnings>136295</retainedEarnings>
      <ownersEquity>4886295</ownersEquity>
      <totalLiabilitiesAndOwnersEquity>5487819</totalLiabilitiesAndOwnersEquity>
    </BalanceSheetObject>
    <BalanceSheetObject>
      <dayOfTheMonth>2</dayOfTheMonth>
      <month>July</month>
      <year>2017</year>
      <day>Sunday</day>
      <numberOfWeeks>4</numberOfWeeks>
      <cashAtBank>333477.6</cashAtBank>
      <accountsReceivable>25648.082</accountsReceivable>
      <inventories>13757</inventories>
      <totalCurrentAssets>352812.6</totalCurrentAssets>
      <propretyAndEquipment>5200641</propretyAndEquipment>
      <totalAssets>5553453.5</totalAssets>
      <accountsPayable>16128</accountsPayable>
      <carbonOffsetReceipts>0</carbonOffsetReceipts>
      <incomeTaxPayable>0</incomeTaxPayable>
      <dividendOwed>0</dividendOwed>
      <currentMaturityofLongtermDebt>0</currentMaturityofLongtermDebt>
      <totalCurrentLiabilities>16128</totalCurrentLiabilities>
      <longTermDebt>0</longTermDebt>
      <shareCapital>4750000</shareCapital>
      <retainedEarnings>136295</retainedEarnings>
      <ownersEquity>4886295</ownersEquity>
      <totalLiabilitiesAndOwnersEquity>5487819</totalLiabilitiesAndOwnersEquity>
    </BalanceSheetObject>
    <BalanceSheetObject>
      <dayOfTheMonth>30</dayOfTheMonth>
      <month>July</month>
      <year>2017</year>
      <day>Sunday</day>
      <numberOfWeeks>4</numberOfWeeks>
      <cashAtBank>353914.5</cashAtBank>
      <accountsReceivable>26044.92</accountsReceivable>
      <inventories>13757</inventories>
      <totalCurrentAssets>373279.5</totalCurrentAssets>
      <propretyAndEquipment>5200641</propretyAndEquipment>
      <totalAssets>5573920.5</totalAssets>
      <accountsPayable>16128</accountsPayable>
      <carbonOffsetReceipts>0</carbonOffsetReceipts>
      <incomeTaxPayable>0</incomeTaxPayable>
      <dividendOwed>0</dividendOwed>
      <currentMaturityofLongtermDebt>0</currentMaturityofLongtermDebt>
      <totalCurrentLiabilities>16128</totalCurrentLiabilities>
      <longTermDebt>0</longTermDebt>
      <shareCapital>4750000</shareCapital>
      <retainedEarnings>136295</retainedEarnings>
      <ownersEquity>4886295</ownersEquity>
      <totalLiabilitiesAndOwnersEquity>5487819</totalLiabilitiesAndOwnersEquity>
    </BalanceSheetObject>
    <BalanceSheetObject>
      <dayOfTheMonth>3</dayOfTheMonth>
      <month>September</month>
      <year>2017</year>
      <day>Sunday</day>
      <numberOfWeeks>4</numberOfWeeks>
      <cashAtBank>378881.938</cashAtBank>
      <accountsReceivable>31757.4453</accountsReceivable>
      <inventories>13757</inventories>
      <totalCurrentAssets>399428.938</totalCurrentAssets>
      <propretyAndEquipment>5200641</propretyAndEquipment>
      <totalAssets>5600070</totalAssets>
      <accountsPayable>20160</accountsPayable>
      <carbonOffsetReceipts>0</carbonOffsetReceipts>
      <incomeTaxPayable>0</incomeTaxPayable>
      <dividendOwed>0</dividendOwed>
      <currentMaturityofLongtermDebt>0</currentMaturityofLongtermDebt>
      <totalCurrentLiabilities>20160</totalCurrentLiabilities>
      <longTermDebt>0</longTermDebt>
      <shareCapital>4750000</shareCapital>
      <retainedEarnings>136295</retainedEarnings>
      <ownersEquity>4886295</ownersEquity>
      <totalLiabilitiesAndOwnersEquity>5487819</totalLiabilitiesAndOwnersEquity>
    </BalanceSheetObject>
    <BalanceSheetObject>
      <dayOfTheMonth>1</dayOfTheMonth>
      <month>October</month>
      <year>2017</year>
      <day>Sunday</day>
      <numberOfWeeks>4</numberOfWeeks>
      <cashAtBank>397014.438</cashAtBank>
      <accountsReceivable>24365.4961</accountsReceivable>
      <inventories>13757</inventories>
      <totalCurrentAssets>417004.438</totalCurrentAssets>
      <propretyAndEquipment>5200641</propretyAndEquipment>
      <totalAssets>5617645.5</totalAssets>
      <accountsPayable>16128</accountsPayable>
      <carbonOffsetReceipts>0</carbonOffsetReceipts>
      <incomeTaxPayable>0</incomeTaxPayable>
      <dividendOwed>0</dividendOwed>
      <currentMaturityofLongtermDebt>0</currentMaturityofLongtermDebt>
      <totalCurrentLiabilities>16128</totalCurrentLiabilities>
      <longTermDebt>0</longTermDebt>
      <shareCapital>4750000</shareCapital>
      <retainedEarnings>136295</retainedEarnings>
      <ownersEquity>4886295</ownersEquity>
      <totalLiabilitiesAndOwnersEquity>5487819</totalLiabilitiesAndOwnersEquity>
    </BalanceSheetObject>
    <BalanceSheetObject>
      <dayOfTheMonth>29</dayOfTheMonth>
      <month>October</month>
      <year>2017</year>
      <day>Sunday</day>
      <numberOfWeeks>4</numberOfWeeks>
      <cashAtBank>415016</cashAtBank>
      <accountsReceivable>24144.5723</accountsReceivable>
      <inventories>13757</inventories>
      <totalCurrentAssets>434916</totalCurrentAssets>
      <propretyAndEquipment>5200641</propretyAndEquipment>
      <totalAssets>5635557</totalAssets>
      <accountsPayable>16128</accountsPayable>
      <carbonOffsetReceipts>0</carbonOffsetReceipts>
      <incomeTaxPayable>0</incomeTaxPayable>
      <dividendOwed>0</dividendOwed>
      <currentMaturityofLongtermDebt>0</currentMaturityofLongtermDebt>
      <totalCurrentLiabilities>16128</totalCurrentLiabilities>
      <longTermDebt>0</longTermDebt>
      <shareCapital>4750000</shareCapital>
      <retainedEarnings>136295</retainedEarnings>
      <ownersEquity>4886295</ownersEquity>
      <totalLiabilitiesAndOwnersEquity>5487819</totalLiabilitiesAndOwnersEquity>
    </BalanceSheetObject>
    <BalanceSheetObject>
      <dayOfTheMonth>3</dayOfTheMonth>
      <month>December</month>
      <year>2017</year>
      <day>Sunday</day>
      <numberOfWeeks>4</numberOfWeeks>
      <cashAtBank>438317.656</cashAtBank>
      <accountsReceivable>30971.6523</accountsReceivable>
      <inventories>13757</inventories>
      <totalCurrentAssets>459744.656</totalCurrentAssets>
      <propretyAndEquipment>5200641</propretyAndEquipment>
      <totalAssets>5660385.5</totalAssets>
      <accountsPayable>20160</accountsPayable>
      <carbonOffsetReceipts>0</carbonOffsetReceipts>
      <incomeTaxPayable>0</incomeTaxPayable>
      <dividendOwed>0</dividendOwed>
      <currentMaturityofLongtermDebt>0</currentMaturityofLongtermDebt>
      <totalCurrentLiabilities>20160</totalCurrentLiabilities>
      <longTermDebt>0</longTermDebt>
      <shareCapital>4750000</shareCapital>
      <retainedEarnings>136295</retainedEarnings>
      <ownersEquity>4886295</ownersEquity>
      <totalLiabilitiesAndOwnersEquity>5487819</totalLiabilitiesAndOwnersEquity>
    </BalanceSheetObject>
    <BalanceSheetObject>
      <dayOfTheMonth>7</dayOfTheMonth>
      <month>January</month>
      <year>2018</year>
      <day>Sunday</day>
      <numberOfWeeks>4</numberOfWeeks>
      <cashAtBank>463640.5</cashAtBank>
      <accountsReceivable>32142.8281</accountsReceivable>
      <inventories>13757</inventories>
      <totalCurrentAssets>484217.5</totalCurrentAssets>
      <propretyAndEquipment>5200641</propretyAndEquipment>
      <totalAssets>5684858.5</totalAssets>
      <accountsPayable>20160</accountsPayable>
      <carbonOffsetReceipts>0</carbonOffsetReceipts>
      <incomeTaxPayable>0</incomeTaxPayable>
      <dividendOwed>0</dividendOwed>
      <currentMaturityofLongtermDebt>0</currentMaturityofLongtermDebt>
      <totalCurrentLiabilities>20160</totalCurrentLiabilities>
      <longTermDebt>0</longTermDebt>
      <shareCapital>4750000</shareCapital>
      <retainedEarnings>136295</retainedEarnings>
      <ownersEquity>4886295</ownersEquity>
      <totalLiabilitiesAndOwnersEquity>5487819</totalLiabilitiesAndOwnersEquity>
    </BalanceSheetObject>
  </BalanceSheetArray>
</BalanceSheets>